vtk_rag/__init__.py
vtk_rag/build.py
vtk_rag/cli.py
vtk_rag/config.py
vtk_rag/chunking/__init__.py
vtk_rag/chunking/chunker.py
vtk_rag/chunking/code/__init__.py
vtk_rag/chunking/code/chunker.py
vtk_rag/chunking/code/models.py
vtk_rag/chunking/code/semantic_chunk.py
vtk_rag/chunking/code/lifecycle/__init__.py
vtk_rag/chunking/code/lifecycle/analyzer.py
vtk_rag/chunking/code/lifecycle/builder.py
vtk_rag/chunking/code/lifecycle/grouper.py
vtk_rag/chunking/code/lifecycle/models.py
vtk_rag/chunking/code/lifecycle/utils.py
vtk_rag/chunking/code/lifecycle/visitor.py
vtk_rag/chunking/code/lifecycle/vtk_knowledge.py
vtk_rag/chunking/doc/__init__.py
vtk_rag/chunking/doc/chunker.py
vtk_rag/chunking/doc/models.py
vtk_rag/chunking/query/__init__.py
vtk_rag/chunking/query/semantic_query.py
vtk_rag/indexing/__init__.py
vtk_rag/indexing/indexer.py
vtk_rag/indexing/models.py
vtk_rag/mcp/__init__.py
vtk_rag/mcp/client.py
vtk_rag/rag/__init__.py
vtk_rag/rag/client.py
vtk_rag/retrieval/__init__.py
vtk_rag/retrieval/models.py
vtk_rag/retrieval/retriever.py
vtk_rag-1.0.0.dist-info/METADATA
vtk_rag-1.0.0.dist-info/WHEEL
vtk_rag-1.0.0.dist-info/entry_points.txt
vtk_rag-1.0.0.dist-info/top_level.txt
vtk_rag-1.0.0.dist-info/RECORD
