Metadata-Version: 2.4
Name: vtk-rag
Version: 1.0.0
Summary: Retrieval-Augmented Generation for VTK code and documentation
Author: Patrick O'Leary
License: MIT
Project-URL: Homepage, https://github.com/patrickoleary/vtk-rag
Project-URL: Repository, https://github.com/patrickoleary/vtk-rag
Project-URL: Documentation, https://github.com/patrickoleary/vtk-rag#readme
Keywords: vtk,rag,retrieval,visualization,search,qdrant
Classifier: Development Status :: 4 - Beta
Classifier: Intended Audience :: Developers
Classifier: Intended Audience :: Science/Research
Classifier: License :: OSI Approved :: MIT License
Classifier: Operating System :: OS Independent
Classifier: Programming Language :: Python :: 3
Classifier: Programming Language :: Python :: 3.10
Classifier: Programming Language :: Python :: 3.11
Classifier: Programming Language :: Python :: 3.12
Classifier: Programming Language :: Python :: 3.13
Classifier: Topic :: Scientific/Engineering :: Visualization
Classifier: Topic :: Software Development :: Libraries :: Python Modules
Requires-Python: >=3.10
Requires-Dist: qdrant-client>=1.7.0
Requires-Dist: sentence-transformers>=2.2.0
Requires-Dist: fastembed>=0.2.0
Requires-Dist: mcp>=1.0.0
Requires-Dist: vtkapi-mcp==1.4.0
Requires-Dist: python-dotenv>=1.0.0
Requires-Dist: vtk>=9.0.0
Provides-Extra: dev
Requires-Dist: pytest>=7.0.0; extra == "dev"
Requires-Dist: pytest-cov>=4.0.0; extra == "dev"
Requires-Dist: ruff>=0.8.0; extra == "dev"
